pyspeaker/Audio.py
pyspeaker/__init__.py
pyspeaker-10.0.dist-info/LICENSE.txt
pyspeaker-10.0.dist-info/METADATA
pyspeaker-10.0.dist-info/WHEEL
pyspeaker-10.0.dist-info/top_level.txt
pyspeaker-10.0.dist-info/RECORD
